<?xml version="1.0" encoding="utf-8"?>
<?xml-stylesheet type='text/xsl' href='../../ld2webpage.xsl'?>
<LOBBYINGDISCLOSURE2>
  <imported>Y</imported>
  <pages>8</pages>
  <submitURL>
  </submitURL>
  <organizationName>MorphoTrust USA (formerly known as L-1 Identity Solutions)</organizationName>
  <prefix>
  </prefix>
  <firstName>
  </firstName>
  <lastName>
  </lastName>
  <registrantDifferentAddress>Y</registrantDifferentAddress>
  <address1>1255 23rd St., NW</address1>
  <address2>Suite 800</address2>
  <city>Washington</city>
  <state>DC</state>
  <zip>20037</zip>
  <zipext>
  </zipext>
  <country>USA</country>
  <principal_city>Billerica</principal_city>
  <principal_state>MA</principal_state>
  <principal_zip>01821</principal_zip>
  <principal_zipext>
  </principal_zipext>
  <principal_country>USA</principal_country>
  <contactIntlPhone>
  </contactIntlPhone>
  <selfSelect>Y</selfSelect>
  <clientName>MorphoTrust USA (formerly known as L-1 Identity Solutions)</clientName>
  <clientGovtEntity>N</clientGovtEntity>
  <senateID>40013100-36</senateID>
  <houseID>393410000</houseID>
  <reportYear>2016</reportYear>
  <reportType>Q1</reportType>
  <terminationDate>
  </terminationDate>
  <noLobbying>
  </noLobbying>
  <income>
  </income>
  <expenses>160000.00</expenses>
  <expensesMethod>A</expensesMethod>
  <printedName>Charles Taylor</printedName>
  <signedDate>4/18/2016 5:31:48 PM</signedDate>
  <alis>
    <ali_info>
      <issueAreaCode>HOM</issueAreaCode>
      <specific_issues>
        <description>Consolidated Appropriations Act of 2016; FY16 DHS Appropriations; travel documents; identification documents; TSA airport operations; TSA PreCheck Expansion Act, HR 2843; Securing Expedited Screening Act, HR 2127; CBP operations; Entry-Exit, HR 229.</description>
      </specific_issues>
      <federal_agencies>U.S. SENATE, U.S. HOUSE OF REPRESENTATIVES, Transportation Security Administration (TSA), Homeland Security - Dept of  (DHS), U.S. Customs &amp; Border Protection, U.S. Citizenship &amp; Immigration Services (USCIS)</federal_agencies>
      <lobbyists>
        <lobbyist>
          <lobbyistFirstName>Jason</lobbyistFirstName>
          <lobbyistLastName>Conley</lobbyistLastName>
          <lobbyistSuffix>
          </lobbyistSuffix>
          <coveredPosition>TSA, Assistant Administrator, Office of Legislative Affairs</coveredPosition>
          <lobbyistNew>N</lobbyistNew>
        </lobbyist>
        <lobbyist>
          <lobbyistFirstName>Benjamin </lobbyistFirstName>
          <lobbyistLastName>Silverstein</lobbyistLastName>
          <lobbyistSuffix>
          </lobbyistSuffix>
          <coveredPosition>
          </coveredPosition>
          <lobbyistNew>N</lobbyistNew>
        </lobbyist>
        <lobbyist>
          <lobbyistFirstName>
          </lobbyistFirstName>
          <lobbyistLastName>
          </lobbyistLastName>
          <lobbyistSuffix>
          </lobbyistSuffix>
          <coveredPosition>
          </coveredPosition>
          <lobbyistNew>N</lobbyistNew>
        </lobbyist>
        <lobbyist>
          <lobbyistFirstName>
          </lobbyistFirstName>
          <lobbyistLastName>
          </lobbyistLastName>
          <lobbyistSuffix>
          </lobbyistSuffix>
          <coveredPosition>
          </coveredPosition>
          <lobbyistNew>N</lobbyistNew>
        </lobbyist>
        <lobbyist>
          <lobbyistFirstName>
          </lobbyistFirstName>
          <lobbyistLastName>
          </lobbyistLastName>
          <lobbyistSuffix>
          </lobbyistSuffix>
          <coveredPosition>
          </coveredPosition>
          <lobbyistNew>N</lobbyistNew>
        </lobbyist>
        <lobbyist>
          <lobbyistFirstName>
          </lobbyistFirstName>
          <lobbyistLastName>
          </lobbyistLastName>
          <lobbyistSuffix>
          </lobbyistSuffix>
          <coveredPosition>
          </coveredPosition>
          <lobbyistNew>N</lobbyistNew>
        </lobbyist>
        <lobbyist>
          <lobbyistFirstName>
          </lobbyistFirstName>
          <lobbyistLastName>
          </lobbyistLastName>
          <lobbyistSuffix>
          </lobbyistSuffix>
          <coveredPosition>
          </coveredPosition>
          <lobbyistNew>N</lobbyistNew>
        </lobbyist>
        <lobbyist>
          <lobbyistFirstName>
          </lobbyistFirstName>
          <lobbyistLastName>
          </lobbyistLastName>
          <lobbyistSuffix>
          </lobbyistSuffix>
          <coveredPosition>
          </coveredPosition>
          <lobbyistNew>N</lobbyistNew>
        </lobbyist>
        <lobbyist>
          <lobbyistFirstName>
          </lobbyistFirstName>
          <lobbyistLastName>
          </lobbyistLastName>
          <lobbyistSuffix>
          </lobbyistSuffix>
          <coveredPosition>
          </coveredPosition>
          <lobbyistNew>N</lobbyistNew>
        </lobbyist>
      </lobbyists>
      <foreign_entity_issues>
      </foreign_entity_issues>
    </ali_info>
    <ali_info>
      <issueAreaCode>IMM</issueAreaCode>
      <specific_issues>
        <description>FY16 DHS Appropriations; travel documents; identification documents; TSA airport operations; TSA PreCheck Expansion Act, HR 2843; Securing Expedited Screening Act, HR 2127; CBP operations; Entry-Exit, HR 229; unaccompanied alien minors; Consolidated Appropriations Act of 2016</description>
      </specific_issues>
      <federal_agencies>U.S. SENATE, U.S. HOUSE OF REPRESENTATIVES, Homeland Security - Dept of  (DHS), U.S. Citizenship &amp; Immigration Services (USCIS), U.S. Customs &amp; Border Protection, U.S. Immigration &amp; Customs Enforcement (ICE), Health &amp; Human Services - Dept of (HHS)</federal_agencies>
      <lobbyists>
        <lobbyist>
          <lobbyistFirstName>Jason </lobbyistFirstName>
          <lobbyistLastName>Conley</lobbyistLastName>
          <lobbyistSuffix>
          </lobbyistSuffix>
          <coveredPosition>Assistant Administrator, TSA, Office of Legislative Affairs</coveredPosition>
          <lobbyistNew>N</lobbyistNew>
        </lobbyist>
        <lobbyist>
          <lobbyistFirstName>Benjamin</lobbyistFirstName>
          <lobbyistLastName>Silverstein</lobbyistLastName>
          <lobbyistSuffix>
          </lobbyistSuffix>
          <coveredPosition>
          </coveredPosition>
          <lobbyistNew>N</lobbyistNew>
        </lobbyist>
        <lobbyist>
          <lobbyistFirstName>
          </lobbyistFirstName>
          <lobbyistLastName>
          </lobbyistLastName>
          <lobbyistSuffix>
          </lobbyistSuffix>
          <coveredPosition>
          </coveredPosition>
          <lobbyistNew>N</lobbyistNew>
        </lobbyist>
        <lobbyist>
          <lobbyistFirstName>
          </lobbyistFirstName>
          <lobbyistLastName>
          </lobbyistLastName>
          <lobbyistSuffix>
          </lobbyistSuffix>
          <coveredPosition>
          </coveredPosition>
          <lobbyistNew>N</lobbyistNew>
        </lobbyist>
        <lobbyist>
          <lobbyistFirstName>
          </lobbyistFirstName>
          <lobbyistLastName>
          </lobbyistLastName>
          <lobbyistSuffix>
          </lobbyistSuffix>
          <coveredPosition>
          </coveredPosition>
          <lobbyistNew>N</lobbyistNew>
        </lobbyist>
        <lobbyist>
          <lobbyistFirstName>
          </lobbyistFirstName>
          <lobbyistLastName>
          </lobbyistLastName>
          <lobbyistSuffix>
          </lobbyistSuffix>
          <coveredPosition>
          </coveredPosition>
          <lobbyistNew>N</lobbyistNew>
        </lobbyist>
        <lobbyist>
          <lobbyistFirstName>
          </lobbyistFirstName>
          <lobbyistLastName>
          </lobbyistLastName>
          <lobbyistSuffix>
          </lobbyistSuffix>
          <coveredPosition>
          </coveredPosition>
          <lobbyistNew>N</lobbyistNew>
        </lobbyist>
        <lobbyist>
          <lobbyistFirstName>
          </lobbyistFirstName>
          <lobbyistLastName>
          </lobbyistLastName>
          <lobbyistSuffix>
          </lobbyistSuffix>
          <coveredPosition>
          </coveredPosition>
          <lobbyistNew>N</lobbyistNew>
        </lobbyist>
        <lobbyist>
          <lobbyistFirstName>
          </lobbyistFirstName>
          <lobbyistLastName>
          </lobbyistLastName>
          <lobbyistSuffix>
          </lobbyistSuffix>
          <coveredPosition>
          </coveredPosition>
          <lobbyistNew>N</lobbyistNew>
        </lobbyist>
      </lobbyists>
      <foreign_entity_issues>
      </foreign_entity_issues>
    </ali_info>
    <ali_info>
      <issueAreaCode>BUD</issueAreaCode>
      <specific_issues>
        <description>FY16 DHS Appropriations; travel documents; identification documents; TSA airport operations; TSA PreCheck Expansion Act, HR 2843; Securing Expedited Screening Act, HR 2127; CBP operations; Entry-Exit, HR 229; Consolidated Appropriations Act of 2016</description>
      </specific_issues>
      <federal_agencies>U.S. SENATE, U.S. HOUSE OF REPRESENTATIVES, Homeland Security - Dept of  (DHS), Office of Management &amp; Budget (OMB), Transportation Security Administration (TSA), U.S. Citizenship &amp; Immigration Services (USCIS), U.S. Customs &amp; Border Protection</federal_agencies>
      <lobbyists>
        <lobbyist>
          <lobbyistFirstName>Jason</lobbyistFirstName>
          <lobbyistLastName>Conley</lobbyistLastName>
          <lobbyistSuffix>
          </lobbyistSuffix>
          <coveredPosition>Assistant Administrator, TSA, Office of Legislative Affairs</coveredPosition>
          <lobbyistNew>N</lobbyistNew>
        </lobbyist>
        <lobbyist>
          <lobbyistFirstName>Benjamin</lobbyistFirstName>
          <lobbyistLastName>Silverstein</lobbyistLastName>
          <lobbyistSuffix>
          </lobbyistSuffix>
          <coveredPosition>
          </coveredPosition>
          <lobbyistNew>N</lobbyistNew>
        </lobbyist>
        <lobbyist>
          <lobbyistFirstName>
          </lobbyistFirstName>
          <lobbyistLastName>
          </lobbyistLastName>
          <lobbyistSuffix>
          </lobbyistSuffix>
          <coveredPosition>
          </coveredPosition>
          <lobbyistNew>N</lobbyistNew>
        </lobbyist>
        <lobbyist>
          <lobbyistFirstName>
          </lobbyistFirstName>
          <lobbyistLastName>
          </lobbyistLastName>
          <lobbyistSuffix>
          </lobbyistSuffix>
          <coveredPosition>
          </coveredPosition>
          <lobbyistNew>N</lobbyistNew>
        </lobbyist>
        <lobbyist>
          <lobbyistFirstName>
          </lobbyistFirstName>
          <lobbyistLastName>
          </lobbyistLastName>
          <lobbyistSuffix>
          </lobbyistSuffix>
          <coveredPosition>
          </coveredPosition>
          <lobbyistNew>N</lobbyistNew>
        </lobbyist>
        <lobbyist>
          <lobbyistFirstName>
          </lobbyistFirstName>
          <lobbyistLastName>
          </lobbyistLastName>
          <lobbyistSuffix>
          </lobbyistSuffix>
          <coveredPosition>
          </coveredPosition>
          <lobbyistNew>N</lobbyistNew>
        </lobbyist>
        <lobbyist>
          <lobbyistFirstName>
          </lobbyistFirstName>
          <lobbyistLastName>
          </lobbyistLastName>
          <lobbyistSuffix>
          </lobbyistSuffix>
          <coveredPosition>
          </coveredPosition>
          <lobbyistNew>N</lobbyistNew>
        </lobbyist>
        <lobbyist>
          <lobbyistFirstName>
          </lobbyistFirstName>
          <lobbyistLastName>
          </lobbyistLastName>
          <lobbyistSuffix>
          </lobbyistSuffix>
          <coveredPosition>
          </coveredPosition>
          <lobbyistNew>N</lobbyistNew>
        </lobbyist>
        <lobbyist>
          <lobbyistFirstName>
          </lobbyistFirstName>
          <lobbyistLastName>
          </lobbyistLastName>
          <lobbyistSuffix>
          </lobbyistSuffix>
          <coveredPosition>
          </coveredPosition>
          <lobbyistNew>N</lobbyistNew>
        </lobbyist>
      </lobbyists>
      <foreign_entity_issues>
      </foreign_entity_issues>
    </ali_info>
    <ali_info>
      <issueAreaCode>GOV</issueAreaCode>
      <specific_issues>
        <description>Issues related to government contracts regarding travel and identification documents; HR 3767, Preventing Government Publishing Overreach Act.

Met with Senator Kirk's office to amend HR 3220, the Medicare Common Access Card Act, to support the use of an eID structure

Met with Senator Grassley's staff to discuss the use of DNA in positively identifying sponsors for unaccompanied minors, but this was not tied to a specific bill</description>
      </specific_issues>
      <federal_agencies>U.S. SENATE, U.S. HOUSE OF REPRESENTATIVES, Homeland Security - Dept of (DHS), U.S. Customs &amp; Border Protection, Transportation Security Administration (TSA)</federal_agencies>
      <lobbyists>
        <lobbyist>
          <lobbyistFirstName>Jason</lobbyistFirstName>
          <lobbyistLastName>Conley</lobbyistLastName>
          <lobbyistSuffix>
          </lobbyistSuffix>
          <coveredPosition>Assistant Administrator, TSA, Office of Legislative Affairs</coveredPosition>
          <lobbyistNew>N</lobbyistNew>
        </lobbyist>
        <lobbyist>
          <lobbyistFirstName>Benjamin</lobbyistFirstName>
          <lobbyistLastName>Silverstein</lobbyistLastName>
          <lobbyistSuffix>
          </lobbyistSuffix>
          <coveredPosition>
          </coveredPosition>
          <lobbyistNew>N</lobbyistNew>
        </lobbyist>
        <lobbyist>
          <lobbyistFirstName>
          </lobbyistFirstName>
          <lobbyistLastName>
          </lobbyistLastName>
          <lobbyistSuffix>
          </lobbyistSuffix>
          <coveredPosition>
          </coveredPosition>
          <lobbyistNew>N</lobbyistNew>
        </lobbyist>
        <lobbyist>
          <lobbyistFirstName>
          </lobbyistFirstName>
          <lobbyistLastName>
          </lobbyistLastName>
          <lobbyistSuffix>
          </lobbyistSuffix>
          <coveredPosition>
          </coveredPosition>
          <lobbyistNew>N</lobbyistNew>
        </lobbyist>
        <lobbyist>
          <lobbyistFirstName>
          </lobbyistFirstName>
          <lobbyistLastName>
          </lobbyistLastName>
          <lobbyistSuffix>
          </lobbyistSuffix>
          <coveredPosition>
          </coveredPosition>
          <lobbyistNew>N</lobbyistNew>
        </lobbyist>
        <lobbyist>
          <lobbyistFirstName>
          </lobbyistFirstName>
          <lobbyistLastName>
          </lobbyistLastName>
          <lobbyistSuffix>
          </lobbyistSuffix>
          <coveredPosition>
          </coveredPosition>
          <lobbyistNew>N</lobbyistNew>
        </lobbyist>
        <lobbyist>
          <lobbyistFirstName>
          </lobbyistFirstName>
          <lobbyistLastName>
          </lobbyistLastName>
          <lobbyistSuffix>
          </lobbyistSuffix>
          <coveredPosition>
          </coveredPosition>
          <lobbyistNew>N</lobbyistNew>
        </lobbyist>
        <lobbyist>
          <lobbyistFirstName>
          </lobbyistFirstName>
          <lobbyistLastName>
          </lobbyistLastName>
          <lobbyistSuffix>
          </lobbyistSuffix>
          <coveredPosition>
          </coveredPosition>
          <lobbyistNew>N</lobbyistNew>
        </lobbyist>
        <lobbyist>
          <lobbyistFirstName>
          </lobbyistFirstName>
          <lobbyistLastName>
          </lobbyistLastName>
          <lobbyistSuffix>
          </lobbyistSuffix>
          <coveredPosition>
          </coveredPosition>
          <lobbyistNew>N</lobbyistNew>
        </lobbyist>
      </lobbyists>
      <foreign_entity_issues>
      </foreign_entity_issues>
    </ali_info>
    <ali_info>
      <issueAreaCode>DEF</issueAreaCode>
      <specific_issues>
        <description>Issues related to biometrics; issues related to defense forensics; National Defense Authorization Act for FY16; Defense Appropriations Act for FY16; Consolidated Appropriations Act of 2016.</description>
      </specific_issues>
      <federal_agencies>U.S. SENATE, U.S. HOUSE OF REPRESENTATIVES, Defense - Dept of  (DOD)</federal_agencies>
      <lobbyists>
        <lobbyist>
          <lobbyistFirstName>Jason</lobbyistFirstName>
          <lobbyistLastName>Conley</lobbyistLastName>
          <lobbyistSuffix>
          </lobbyistSuffix>
          <coveredPosition>Assistant Administrator, TSA, Office of Legislative Affairs</coveredPosition>
          <lobbyistNew>N</lobbyistNew>
        </lobbyist>
        <lobbyist>
          <lobbyistFirstName>Benjamin</lobbyistFirstName>
          <lobbyistLastName>Silverstein</lobbyistLastName>
          <lobbyistSuffix>
          </lobbyistSuffix>
          <coveredPosition>
          </coveredPosition>
          <lobbyistNew>N</lobbyistNew>
        </lobbyist>
        <lobbyist>
          <lobbyistFirstName>
          </lobbyistFirstName>
          <lobbyistLastName>
          </lobbyistLastName>
          <lobbyistSuffix>
          </lobbyistSuffix>
          <coveredPosition>
          </coveredPosition>
          <lobbyistNew>N</lobbyistNew>
        </lobbyist>
        <lobbyist>
          <lobbyistFirstName>
          </lobbyistFirstName>
          <lobbyistLastName>
          </lobbyistLastName>
          <lobbyistSuffix>
          </lobbyistSuffix>
          <coveredPosition>
          </coveredPosition>
          <lobbyistNew>N</lobbyistNew>
        </lobbyist>
        <lobbyist>
          <lobbyistFirstName>
          </lobbyistFirstName>
          <lobbyistLastName>
          </lobbyistLastName>
          <lobbyistSuffix>
          </lobbyistSuffix>
          <coveredPosition>
          </coveredPosition>
          <lobbyistNew>N</lobbyistNew>
        </lobbyist>
        <lobbyist>
          <lobbyistFirstName>
          </lobbyistFirstName>
          <lobbyistLastName>
          </lobbyistLastName>
          <lobbyistSuffix>
          </lobbyistSuffix>
          <coveredPosition>
          </coveredPosition>
          <lobbyistNew>N</lobbyistNew>
        </lobbyist>
        <lobbyist>
          <lobbyistFirstName>
          </lobbyistFirstName>
          <lobbyistLastName>
          </lobbyistLastName>
          <lobbyistSuffix>
          </lobbyistSuffix>
          <coveredPosition>
          </coveredPosition>
          <lobbyistNew>N</lobbyistNew>
        </lobbyist>
        <lobbyist>
          <lobbyistFirstName>
          </lobbyistFirstName>
          <lobbyistLastName>
          </lobbyistLastName>
          <lobbyistSuffix>
          </lobbyistSuffix>
          <coveredPosition>
          </coveredPosition>
          <lobbyistNew>N</lobbyistNew>
        </lobbyist>
        <lobbyist>
          <lobbyistFirstName>
          </lobbyistFirstName>
          <lobbyistLastName>
          </lobbyistLastName>
          <lobbyistSuffix>
          </lobbyistSuffix>
          <coveredPosition>
          </coveredPosition>
          <lobbyistNew>N</lobbyistNew>
        </lobbyist>
      </lobbyists>
      <foreign_entity_issues>
      </foreign_entity_issues>
    </ali_info>
    <ali_info>
      <issueAreaCode>TOU</issueAreaCode>
      <specific_issues>
        <description>FY15 DHS Appropriations, HR 240; FY16 DHS Appropriations; travel documents; identification documents; TSA airport operations; TSA PreCheck Expansion Act, HR 2843; Securing Expedited Screening Act, HR 2127; CBP operations; Entry-Exit, HR 229; Consolidated Appropriations Act of 2016.</description>
      </specific_issues>
      <federal_agencies>U.S. SENATE, U.S. HOUSE OF REPRESENTATIVES, Homeland Security - Dept of  (DHS), Office of Management &amp; Budget (OMB), Transportation Security Administration (TSA), U.S. Customs &amp; Border Protection, State - Dept of (DOS), U.S. Citizenship &amp; Immigration Services (USCIS), U.S. Immigration &amp; Customs Enforcement (ICE)</federal_agencies>
      <lobbyists>
        <lobbyist>
          <lobbyistFirstName>Jason</lobbyistFirstName>
          <lobbyistLastName>Conley</lobbyistLastName>
          <lobbyistSuffix>
          </lobbyistSuffix>
          <coveredPosition>Assistant Administrator, TSA, Office of Legislative Affairs</coveredPosition>
          <lobbyistNew>N</lobbyistNew>
        </lobbyist>
        <lobbyist>
          <lobbyistFirstName>Benjamin</lobbyistFirstName>
          <lobbyistLastName>Silverstein</lobbyistLastName>
          <lobbyistSuffix>
          </lobbyistSuffix>
          <coveredPosition>
          </coveredPosition>
          <lobbyistNew>N</lobbyistNew>
        </lobbyist>
        <lobbyist>
          <lobbyistFirstName>
          </lobbyistFirstName>
          <lobbyistLastName>
          </lobbyistLastName>
          <lobbyistSuffix>
          </lobbyistSuffix>
          <coveredPosition>
          </coveredPosition>
          <lobbyistNew>N</lobbyistNew>
        </lobbyist>
        <lobbyist>
          <lobbyistFirstName>
          </lobbyistFirstName>
          <lobbyistLastName>
          </lobbyistLastName>
          <lobbyistSuffix>
          </lobbyistSuffix>
          <coveredPosition>
          </coveredPosition>
          <lobbyistNew>N</lobbyistNew>
        </lobbyist>
        <lobbyist>
          <lobbyistFirstName>
          </lobbyistFirstName>
          <lobbyistLastName>
          </lobbyistLastName>
          <lobbyistSuffix>
          </lobbyistSuffix>
          <coveredPosition>
          </coveredPosition>
          <lobbyistNew>N</lobbyistNew>
        </lobbyist>
        <lobbyist>
          <lobbyistFirstName>
          </lobbyistFirstName>
          <lobbyistLastName>
          </lobbyistLastName>
          <lobbyistSuffix>
          </lobbyistSuffix>
          <coveredPosition>
          </coveredPosition>
          <lobbyistNew>N</lobbyistNew>
        </lobbyist>
        <lobbyist>
          <lobbyistFirstName>
          </lobbyistFirstName>
          <lobbyistLastName>
          </lobbyistLastName>
          <lobbyistSuffix>
          </lobbyistSuffix>
          <coveredPosition>
          </coveredPosition>
          <lobbyistNew>N</lobbyistNew>
        </lobbyist>
        <lobbyist>
          <lobbyistFirstName>
          </lobbyistFirstName>
          <lobbyistLastName>
          </lobbyistLastName>
          <lobbyistSuffix>
          </lobbyistSuffix>
          <coveredPosition>
          </coveredPosition>
          <lobbyistNew>N</lobbyistNew>
        </lobbyist>
        <lobbyist>
          <lobbyistFirstName>
          </lobbyistFirstName>
          <lobbyistLastName>
          </lobbyistLastName>
          <lobbyistSuffix>
          </lobbyistSuffix>
          <coveredPosition>
          </coveredPosition>
          <lobbyistNew>N</lobbyistNew>
        </lobbyist>
      </lobbyists>
      <foreign_entity_issues>
      </foreign_entity_issues>
    </ali_info>
  </alis>
  <updates>
    <clientAddress>
    </clientAddress>
    <clientCity>
    </clientCity>
    <clientState>
    </clientState>
    <clientZip>
    </clientZip>
    <clientZipext>
    </clientZipext>
    <clientCountry>
    </clientCountry>
    <prinClientCity>
    </prinClientCity>
    <prinClientState>
    </prinClientState>
    <prinClientZip>
    </prinClientZip>
    <prinClientZipext>
    </prinClientZipext>
    <prinClientCountry>
    </prinClientCountry>
    <generalDescription>
    </generalDescription>
    <inactive_lobbyists>
      <inactive_lobbyist>
        <firstName>
        </firstName>
        <lastName>
        </lastName>
        <suffix>
        </suffix>
      </inactive_lobbyist>
      <inactive_lobbyist>
        <firstName>
        </firstName>
        <lastName>
        </lastName>
        <suffix>
        </suffix>
      </inactive_lobbyist>
      <inactive_lobbyist>
        <firstName>
        </firstName>
        <lastName>
        </lastName>
        <suffix>
        </suffix>
      </inactive_lobbyist>
      <inactive_lobbyist>
        <firstName>
        </firstName>
        <lastName>
        </lastName>
        <suffix>
        </suffix>
      </inactive_lobbyist>
    </inactive_lobbyists>
    <inactive_ALIs>
      <ali_Code>
      </ali_Code>
      <ali_Code>
      </ali_Code>
      <ali_Code>
      </ali_Code>
      <ali_Code>
      </ali_Code>
      <ali_Code>
      </ali_Code>
      <ali_Code>
      </ali_Code>
      <ali_Code>
      </ali_Code>
      <ali_Code>
      </ali_Code>
      <ali_Code>
      </ali_Code>
    </inactive_ALIs>
    <affiliatedUrl>
    </affiliatedUrl>
    <affiliatedOrgs>
      <affiliatedOrg>
        <affiliatedOrgName>
        </affiliatedOrgName>
        <affiliatedOrgAddress>
        </affiliatedOrgAddress>
        <affiliatedOrgCity>
        </affiliatedOrgCity>
        <affiliatedOrgState>
        </affiliatedOrgState>
        <affiliatedOrgZip>
        </affiliatedOrgZip>
        <affiliatedOrgCountry>
        </affiliatedOrgCountry>
        <affiliatedPrinOrgCity>
        </affiliatedPrinOrgCity>
        <affiliatedPrinOrgState>
        </affiliatedPrinOrgState>
        <affiliatedPrinOrgCountry>
        </affiliatedPrinOrgCountry>
      </affiliatedOrg>
      <affiliatedOrg>
        <affiliatedOrgName>
        </affiliatedOrgName>
        <affiliatedOrgAddress>
        </affiliatedOrgAddress>
        <affiliatedOrgCity>
        </affiliatedOrgCity>
        <affiliatedOrgState>
        </affiliatedOrgState>
        <affiliatedOrgZip>
        </affiliatedOrgZip>
        <affiliatedOrgCountry>
        </affiliatedOrgCountry>
        <affiliatedPrinOrgCity>
        </affiliatedPrinOrgCity>
        <affiliatedPrinOrgState>
        </affiliatedPrinOrgState>
        <affiliatedPrinOrgCountry>
        </affiliatedPrinOrgCountry>
      </affiliatedOrg>
    </affiliatedOrgs>
    <inactiveOrgs>
      <inactiveOrgName>
      </inactiveOrgName>
      <inactiveOrgName>
      </inactiveOrgName>
      <inactiveOrgName>
      </inactiveOrgName>
    </inactiveOrgs>
    <foreignEntities>
      <foreignEntity>
        <name>
        </name>
        <address>
        </address>
        <city>
        </city>
        <state>
        </state>
        <country>
        </country>
        <prinCity>
        </prinCity>
        <prinState>
        </prinState>
        <prinCountry>
        </prinCountry>
        <contribution>
        </contribution>
        <ownership_Percentage>
        </ownership_Percentage>
      </foreignEntity>
    </foreignEntities>
    <inactive_ForeignEntities>
      <inactive_ForeignEntity>
      </inactive_ForeignEntity>
      <inactive_ForeignEntity>
      </inactive_ForeignEntity>
      <inactive_ForeignEntity>
      </inactive_ForeignEntity>
      <inactive_ForeignEntity>
      </inactive_ForeignEntity>
      <inactive_ForeignEntity>
      </inactive_ForeignEntity>
      <inactive_ForeignEntity>
      </inactive_ForeignEntity>
    </inactive_ForeignEntities>
  </updates>
</LOBBYINGDISCLOSURE2>